tflite_runtime/__init__.py
tflite_runtime/_pywrap_tensorflow_interpreter_wrapper.so
tflite_runtime/interpreter.py
tflite_runtime/metrics_interface.py
tflite_runtime/metrics_portable.py
tflite_runtime-2.12.0.dist-info/METADATA
tflite_runtime-2.12.0.dist-info/WHEEL
tflite_runtime-2.12.0.dist-info/top_level.txt
tflite_runtime-2.12.0.dist-info/RECORD
